frasco_menu.py
setup.py
frasco_menu.egg-info/PKG-INFO
frasco_menu.egg-info/SOURCES.txt
frasco_menu.egg-info/dependency_links.txt
frasco_menu.egg-info/not-zip-safe
frasco_menu.egg-info/requires.txt
frasco_menu.egg-info/top_level.txt