Metadata-Version: 1.0
Name: frasco-menu
Version: 0.2
Summary: Menu management for Frasco
Home-page: http://github.com/frascoweb/frasco-menu
Author: Maxime Bouroumeau-Fuseau
Author-email: maxime.bouroumeau@gmail.com
License: MIT
Platform: any
